{"id":13,"name":"Echo","class":"Sonar","sail_number":"571","club":"LYC","stats":{"total_races":199,"seasons":15,"first_year":2011,"last_year":2025,"wins":72,"podiums":139,"avg_finish":2.9},"seasons":[{"year":2011,"races":17,"wins":3,"avg_finish":4.2},{"year":2012,"races":5,"wins":3,"avg_finish":3.8},{"year":2013,"races":27,"wins":5,"avg_finish":4.3},{"year":2014,"races":14,"wins":5,"avg_finish":3.6},{"year":2015,"races":9,"wins":3,"avg_finish":3.3},{"year":2016,"races":16,"wins":3,"avg_finish":3.1},{"year":2017,"races":19,"wins":6,"avg_finish":2.3},{"year":2018,"races":10,"wins":6,"avg_finish":1.4},{"year":2019,"races":18,"wins":5,"avg_finish":2.5},{"year":2020,"races":10,"wins":5,"avg_finish":2.0},{"year":2021,"races":17,"wins":11,"avg_finish":1.6},{"year":2022,"races":9,"wins":3,"avg_finish":3.2},{"year":2023,"races":8,"wins":4,"avg_finish":1.9},{"year":2024,"races":13,"wins":7,"avg_finish":1.8},{"year":2025,"races":7,"wins":3,"avg_finish":1.6}],"trophies":[{"year":2024,"name":"LYC Handicap - August Thrusday Night Series - Glube Cup/Sauerkraut Cup","event_type":"tns","summary_scope":"s_division","nett_points":3.0},{"year":2024,"name":"LYC Handicap - August Thrusday Night Series - Glube Cup/Sauerkraut Cup OVERALL","event_type":"tns","summary_scope":"s_division","nett_points":3.0},{"year":2023,"name":"LYC Handicap Glube Cup/Sauerkraut Cup - August TNS Mahone Marine","event_type":"tns","summary_scope":"s_division","nett_points":3.5},{"year":2023,"name":"LYC Handicap Glube Cup/Sauerkraut Cup - August TNS Mahone Marine","event_type":"tns","summary_scope":"s_division","nett_points":3.5},{"year":2022,"name":"LYC Handicap - August TNS","event_type":"tns","summary_scope":"s_division","nett_points":5.0},{"year":2022,"name":"LYC Handicap - August TNS Overall","event_type":"tns","summary_scope":"s_division","nett_points":5.0},{"year":2021,"name":"LYC Handicap - Sept TNS Prince's Inlet Cup OVERALL","event_type":"tns","summary_scope":"s_division","nett_points":2.0},{"year":2021,"name":"LYC Handicap - Sept TNS Prince's |Inlet Cup","event_type":"tns","summary_scope":"s_division","nett_points":2.0},{"year":2021,"name":"LYC Thursday Night Series - Michele Stevens July TNS","event_type":"tns","summary_scope":"s_division","nett_points":4.0},{"year":2021,"name":"LYC Thursday Night Series - Michele Stevens July TNS","event_type":"tns","summary_scope":"s_division","nett_points":4.0},{"year":2020,"name":"LYC Handicap - September TNS - Prince's Inlet Cup","event_type":"tns","summary_scope":"s_division","nett_points":3.0},{"year":2020,"name":"LYC Handicap - September TNS - Prince's Inlet Cup OVERALL","event_type":"tns","summary_scope":"s_division","nett_points":3.0},{"year":2018,"name":"LYC Handicap - Mahone Marine July TNS","event_type":"tns","summary_scope":"s_division","nett_points":3.0},{"year":2018,"name":"LYC Handicap - Mahone Marine July TNS","event_type":"tns","summary_scope":"s_division","nett_points":3.0},{"year":2018,"name":"LYC Handicap - September TNS West Nova Fuels","event_type":"tns","summary_scope":"s_division","nett_points":4.0},{"year":2018,"name":"LYC Handicap - September TNS West Nova Fuels OVERALL","event_type":"tns","summary_scope":"s_division","nett_points":4.0},{"year":2017,"name":"LYC Handicap - Mahone Marine August TNS","event_type":"tns","summary_scope":"s_division","nett_points":4.0},{"year":2017,"name":"LYC Handicap - September TNS","event_type":"tns","summary_scope":"s_division","nett_points":3.0},{"year":2016,"name":"LYC Handicap - August TNS A, B, S fleets","event_type":"tns","summary_scope":"s_fleet","nett_points":4.0},{"year":2016,"name":"LYC Handicap - West Nova Fuels September TNS","event_type":"tns","summary_scope":"overall","nett_points":5.0},{"year":2015,"name":"LYC Handicap - July Sunnybrook Yachts & Boat Locker TNS","event_type":"tns","summary_scope":"overall","nett_points":7.0},{"year":2015,"name":"LYC Handicap - July Sunnybrook Yachts & Boat Locker TNS A,B &S","event_type":"tns","summary_scope":"s_fleet","nett_points":4.0},{"year":2015,"name":"LYC Handicap - July Sunnybrook Yachts & Boat Locker TNS Overall","event_type":"tns","summary_scope":"overall","nett_points":7.0},{"year":2015,"name":"LYC Handicap - Mahone Marine August TNS","event_type":"tns","summary_scope":"overall","nett_points":5.0},{"year":2015,"name":"LYC Handicap - Mahone Marine August TNS Overall","event_type":"tns","summary_scope":"s_fleet","nett_points":5.0},{"year":2015,"name":"LYC Handicap - Mahone Marine August TNS Overall","event_type":"tns","summary_scope":"overall","nett_points":5.0},{"year":2014,"name":"LYC Handicap - July Thursday Night Series","event_type":"tns","summary_scope":"s_fleet","nett_points":4.0},{"year":2013,"name":"LYC Handicap - Mahone Marine June TNS","event_type":"tns","summary_scope":"overall","nett_points":9.0},{"year":2013,"name":"LYC Handicap - Mahone Marine June TNS Series A&B","event_type":"tns","summary_scope":"b_fleet","nett_points":4.0},{"year":2013,"name":"LYC Handicap - Mahone Marine June TNS Series Overall","event_type":"tns","summary_scope":"overall","nett_points":6.0},{"year":2013,"name":"LYC Handicap - North Sails Atlantic/Yachtshop July TNS","event_type":"tns","summary_scope":"overall","nett_points":7.0},{"year":2013,"name":"LYC Handicap - North Sails Atlantic/Yachtshop July TNS A & B","event_type":"tns","summary_scope":"b_fleet","nett_points":5.0},{"year":2013,"name":"LYC Handicap - North Sails Atlantic/Yachtshop July TNS Overall","event_type":"tns","summary_scope":"overall","nett_points":6.0}]}