{"id":309,"year":2010,"name":"LYC Sail Fest - Lunenburg Yacht Club","canonical_name":"LYC Sail Fest - Lunenburg Yacht Club","slug":"lyc-sail-fest-lunenburg-yacht-club","event_type":"championship","month":null,"source_format":"sailwave","source_file":"racing1999_2013/racing2010/sailfest2010.htm","scoring_system":"Appendix A","rating_system":null,"races_sailed":6,"discards":1,"to_count":5,"entries":17,"publication_status":"as-of","published_at":null,"notes":null,"season_year":2010,"canonical_event_id":309,"is_variant_view":false,"variant_sources":[{"event_id":309,"name":"LYC Sail Fest - Lunenburg Yacht Club","source_file":"racing1999_2013/racing2010/sailfest2010.htm","race_count":0,"standings_count":27,"result_count":0,"is_primary":true}],"exclude_from_handicap_stats":true,"special_event_kind":"special_external","special_event_reasons":["event_type_championship"],"standings":[{"rank":1,"summary_scope":"overall","fleet":null,"division":null,"phrf_rating":null,"total_points":7.0,"nett_points":5.0,"display_name":"Adam Taylor","participant_type":"helm","sail_number":"5290","raw_class":"420","boat_name":null,"boat_class":null,"boat_id":null},{"rank":1,"summary_scope":"overall","fleet":null,"division":null,"phrf_rating":null,"total_points":9.0,"nett_points":7.0,"display_name":"Karl Mitchell","participant_type":"helm","sail_number":"182790","raw_class":"Laser","boat_name":null,"boat_class":null,"boat_id":null},{"rank":1,"summary_scope":"overall","fleet":null,"division":null,"phrf_rating":null,"total_points":10.0,"nett_points":8.0,"display_name":"Sandy Beatty","participant_type":"helm","sail_number":"193292","raw_class":"Radial","boat_name":null,"boat_class":null,"boat_id":null},{"rank":2,"summary_scope":"overall","fleet":null,"division":null,"phrf_rating":null,"total_points":11.0,"nett_points":9.0,"display_name":"Gavin Hatheway","participant_type":"helm","sail_number":"5294","raw_class":"420","boat_name":null,"boat_class":null,"boat_id":null},{"rank":2,"summary_scope":"overall","fleet":null,"division":null,"phrf_rating":null,"total_points":14.0,"nett_points":11.0,"display_name":"Anthony Bell","participant_type":"helm","sail_number":"210","raw_class":"Laser","boat_name":null,"boat_class":null,"boat_id":null},{"rank":2,"summary_scope":"overall","fleet":null,"division":null,"phrf_rating":null,"total_points":18.0,"nett_points":14.0,"display_name":"Alex Burke","participant_type":"helm","sail_number":"181870","raw_class":"Radial","boat_name":null,"boat_class":null,"boat_id":null},{"rank":3,"summary_scope":"overall","fleet":null,"division":null,"phrf_rating":null,"total_points":24.0,"nett_points":18.0,"display_name":"Griffin Mason","participant_type":"helm","sail_number":"2179","raw_class":"420","boat_name":null,"boat_class":null,"boat_id":null},{"rank":3,"summary_scope":"overall","fleet":null,"division":null,"phrf_rating":null,"total_points":20.0,"nett_points":16.0,"display_name":"David Mosher","participant_type":"helm","sail_number":"183811","raw_class":"Laser","boat_name":null,"boat_class":null,"boat_id":null},{"rank":3,"summary_scope":"overall","fleet":null,"division":null,"phrf_rating":null,"total_points":24.0,"nett_points":18.0,"display_name":"Alex Mann","participant_type":"helm","sail_number":"188978","raw_class":"Radial","boat_name":null,"boat_class":null,"boat_id":null},{"rank":4,"summary_scope":"overall","fleet":null,"division":null,"phrf_rating":null,"total_points":28.0,"nett_points":21.0,"display_name":"Sydney Beatty","participant_type":"helm","sail_number":"9","raw_class":"420","boat_name":null,"boat_class":null,"boat_id":null},{"rank":4,"summary_scope":"overall","fleet":null,"division":null,"phrf_rating":null,"total_points":30.0,"nett_points":23.0,"display_name":"Alexander O'Connor","participant_type":"helm","sail_number":"178548","raw_class":"Radial","boat_name":null,"boat_class":null,"boat_id":null},{"rank":5,"summary_scope":"overall","fleet":null,"division":null,"phrf_rating":null,"total_points":32.0,"nett_points":24.0,"display_name":"Alexe Patenaude","participant_type":"helm","sail_number":"0094","raw_class":"420","boat_name":null,"boat_class":null,"boat_id":null},{"rank":5,"summary_scope":"overall","fleet":null,"division":null,"phrf_rating":null,"total_points":30.0,"nett_points":24.0,"display_name":"Nathan Fields","participant_type":"helm","sail_number":"196283","raw_class":"Radial","boat_name":null,"boat_class":null,"boat_id":null},{"rank":6,"summary_scope":"overall","fleet":null,"division":null,"phrf_rating":null,"total_points":35.0,"nett_points":27.0,"display_name":"Antonia Lewin-La France","participant_type":"helm","sail_number":"5955","raw_class":"420","boat_name":null,"boat_class":null,"boat_id":null},{"rank":6,"summary_scope":"overall","fleet":null,"division":null,"phrf_rating":null,"total_points":39.0,"nett_points":32.0,"display_name":"Jack Bignell","participant_type":"helm","sail_number":"182730","raw_class":"Radial","boat_name":null,"boat_class":null,"boat_id":null},{"rank":7,"summary_scope":"overall","fleet":null,"division":null,"phrf_rating":null,"total_points":37.0,"nett_points":30.0,"display_name":"Soren Wilde","participant_type":"helm","sail_number":"2377","raw_class":"420","boat_name":null,"boat_class":null,"boat_id":null},{"rank":7,"summary_scope":"overall","fleet":null,"division":null,"phrf_rating":null,"total_points":45.0,"nett_points":38.0,"display_name":"Brendan Smith","participant_type":"helm","sail_number":"196030","raw_class":"Radial","boat_name":null,"boat_class":null,"boat_id":null},{"rank":8,"summary_scope":"overall","fleet":null,"division":null,"phrf_rating":null,"total_points":48.0,"nett_points":38.0,"display_name":"AJ Case","participant_type":"helm","sail_number":"4141","raw_class":"420","boat_name":null,"boat_class":null,"boat_id":null},{"rank":9,"summary_scope":"overall","fleet":null,"division":null,"phrf_rating":null,"total_points":52.0,"nett_points":41.0,"display_name":"Claire Hebb","participant_type":"helm","sail_number":"5295","raw_class":"420","boat_name":null,"boat_class":null,"boat_id":null},{"rank":10,"summary_scope":"overall","fleet":null,"division":null,"phrf_rating":null,"total_points":58.0,"nett_points":47.0,"display_name":"Sam Julien","participant_type":"helm","sail_number":"5435","raw_class":"420","boat_name":null,"boat_class":null,"boat_id":null},{"rank":11,"summary_scope":"overall","fleet":null,"division":null,"phrf_rating":null,"total_points":74.0,"nett_points":59.0,"display_name":"Sean Le Blanc","participant_type":"helm","sail_number":"5293","raw_class":"420","boat_name":null,"boat_class":null,"boat_id":null},{"rank":12,"summary_scope":"overall","fleet":null,"division":null,"phrf_rating":null,"total_points":76.0,"nett_points":61.0,"display_name":"Katherine Snelling","participant_type":"helm","sail_number":"2364","raw_class":"420","boat_name":null,"boat_class":null,"boat_id":null},{"rank":13,"summary_scope":"overall","fleet":null,"division":null,"phrf_rating":null,"total_points":83.0,"nett_points":67.0,"display_name":"Justin Smith","participant_type":"helm","sail_number":"5422","raw_class":"420","boat_name":null,"boat_class":null,"boat_id":null},{"rank":14,"summary_scope":"overall","fleet":null,"division":null,"phrf_rating":null,"total_points":85.0,"nett_points":68.0,"display_name":"Holly Foxall","participant_type":"helm","sail_number":"3591","raw_class":"420","boat_name":null,"boat_class":null,"boat_id":null},{"rank":15,"summary_scope":"overall","fleet":null,"division":null,"phrf_rating":null,"total_points":88.0,"nett_points":71.0,"display_name":"Patrick Sawler","participant_type":"helm","sail_number":"3298","raw_class":"420","boat_name":null,"boat_class":null,"boat_id":null},{"rank":16,"summary_scope":"overall","fleet":null,"division":null,"phrf_rating":null,"total_points":89.0,"nett_points":72.0,"display_name":"Adrienne Gaudreault","participant_type":"helm","sail_number":"5292","raw_class":"420","boat_name":null,"boat_class":null,"boat_id":null},{"rank":17,"summary_scope":"overall","fleet":null,"division":null,"phrf_rating":null,"total_points":91.0,"nett_points":75.0,"display_name":"Sasha Foss","participant_type":"helm","sail_number":"537","raw_class":"420","boat_name":null,"boat_class":null,"boat_id":null}],"races":[]}