{"id":605,"year":2004,"name":"Scotia Trawler July Series","canonical_name":"Scotia Trawler July Series","slug":"scotia-trawler-july-series","event_type":"tns","month":"july","source_format":"legacy","source_file":"/Users/grahammann/Coding/lyc-racing-data/racing1999_2013/racing2004/scotia_trawler_july_4.htm","scoring_system":null,"rating_system":null,"races_sailed":4,"discards":null,"to_count":null,"entries":11,"publication_status":"final","published_at":null,"notes":"Wind:  0","season_year":2004,"canonical_event_id":605,"is_variant_view":false,"variant_sources":[{"event_id":602,"name":"Scotia Trawler July Series","source_file":"/Users/grahammann/Coding/lyc-racing-data/racing1999_2013/racing2004/scotia_trawler_july_1.htm","race_count":1,"standings_count":0,"result_count":6,"is_primary":false},{"event_id":603,"name":"Scotia Trawler July Series","source_file":"/Users/grahammann/Coding/lyc-racing-data/racing1999_2013/racing2004/scotia_trawler_july_2.htm","race_count":1,"standings_count":0,"result_count":10,"is_primary":false},{"event_id":604,"name":"Scotia Trawler July Series","source_file":"/Users/grahammann/Coding/lyc-racing-data/racing1999_2013/racing2004/scotia_trawler_july_3.htm","race_count":1,"standings_count":0,"result_count":10,"is_primary":false},{"event_id":605,"name":"Scotia Trawler July Series","source_file":"/Users/grahammann/Coding/lyc-racing-data/racing1999_2013/racing2004/scotia_trawler_july_4.htm","race_count":1,"standings_count":0,"result_count":11,"is_primary":true},{"event_id":606,"name":"Scotia Trawler July Series","source_file":"/Users/grahammann/Coding/lyc-racing-data/racing1999_2013/racing2004/scotia_trawler_july_series.htm","race_count":1,"standings_count":0,"result_count":9,"is_primary":false}],"exclude_from_handicap_stats":false,"special_event_kind":null,"special_event_reasons":[],"standings":[],"races":[{"id":1254,"race_key":"r1","race_number":1,"date":"01/07/2004","start_time":"18:30:00","wind_direction":null,"wind_speed_knots":null,"course":null,"distance_nm":null,"notes":", Course: #25","results":[{"rank":1,"fleet":null,"division":null,"phrf_rating":102,"start_time":"18:30:00","finish_time":"20:14:22","elapsed_time":"00 01:44:22","corrected_time":"00 01:46:27","bcr":null,"points":1.0,"status":null,"display_name":"Tsunami","participant_type":"boat","sail_number":"428","raw_class":"C&C 24","boat_name":"Tsunami","boat_class":"C&C 24","boat_id":43},{"rank":2,"fleet":null,"division":null,"phrf_rating":118,"start_time":"18:30:00","finish_time":"20:00:56","elapsed_time":"00 01:30:56","corrected_time":"00 01:47:18","bcr":null,"points":2.0,"status":null,"display_name":"Topaz","participant_type":"boat","sail_number":"M55","raw_class":"Mega 30","boat_name":"Topaz","boat_class":"Mega 30","boat_id":107},{"rank":3,"fleet":null,"division":null,"phrf_rating":null,"start_time":"18:30:00","finish_time":"20:04:53","elapsed_time":"00 01:34:53","corrected_time":"00 01:47:42","bcr":null,"points":3.0,"status":null,"display_name":"Awesome","participant_type":"boat","sail_number":"203","raw_class":"Kirby 25","boat_name":"Awesome","boat_class":"Kirby 25","boat_id":180},{"rank":4,"fleet":null,"division":null,"phrf_rating":113,"start_time":"18:30:00","finish_time":"20:06:09","elapsed_time":"00 01:36:09","corrected_time":"00 01:48:39","bcr":null,"points":4.0,"status":null,"display_name":"Sly Fox","participant_type":"boat","sail_number":"34142","raw_class":"Chaser 29 Mod.","boat_name":"Sly Fox","boat_class":"Chaser 29 Mod.","boat_id":25},{"rank":5,"fleet":null,"division":null,"phrf_rating":null,"start_time":"18:30:00","finish_time":"20:08:24","elapsed_time":"00 01:38:24","corrected_time":"00 01:48:44","bcr":null,"points":5.0,"status":null,"display_name":"No Name","participant_type":"boat","sail_number":"31297","raw_class":"S2 7.9 IB","boat_name":"No Name","boat_class":"S2 7.9 IB","boat_id":305},{"rank":6,"fleet":null,"division":null,"phrf_rating":null,"start_time":"18:30:00","finish_time":"20:15:35","elapsed_time":"00 01:45:35","corrected_time":"00 01:59:50","bcr":null,"points":6.0,"status":null,"display_name":"Beatnik","participant_type":"boat","sail_number":"186","raw_class":"K25","boat_name":"Beatnik","boat_class":"K25","boat_id":299}]},{"id":1255,"race_key":"r2","race_number":2,"date":"08/07/2004","start_time":"18:30:00","wind_direction":null,"wind_speed_knots":null,"course":null,"distance_nm":null,"notes":", Distance: 1","results":[{"rank":1,"fleet":null,"division":null,"phrf_rating":null,"start_time":"18:30:00","finish_time":"20:52:13","elapsed_time":"00 02:22:13","corrected_time":"00 02:37:09","bcr":null,"points":1.0,"status":null,"display_name":"No Name","participant_type":"boat","sail_number":"31297","raw_class":"S2 7.9 IB","boat_name":"No Name","boat_class":"S2 7.9 IB","boat_id":305},{"rank":2,"fleet":null,"division":null,"phrf_rating":null,"start_time":"18:30:00","finish_time":"20:51:31","elapsed_time":"00 02:21:31","corrected_time":"00 02:40:37","bcr":null,"points":2.0,"status":null,"display_name":"Status Symbol","participant_type":"boat","sail_number":"126","raw_class":"Kirby 25","boat_name":"Status Symbol","boat_class":"Kirby 25","boat_id":265},{"rank":3,"fleet":null,"division":null,"phrf_rating":102,"start_time":"18:30:00","finish_time":"21:09:22","elapsed_time":"00 02:39:22","corrected_time":"00 02:42:33","bcr":null,"points":3.0,"status":null,"display_name":"Tsunami","participant_type":"boat","sail_number":"428","raw_class":"C&C 24","boat_name":"Tsunami","boat_class":"C&C 24","boat_id":43},{"rank":4,"fleet":null,"division":null,"phrf_rating":110,"start_time":"18:30:00","finish_time":"20:59:54","elapsed_time":"00 02:29:54","corrected_time":"00 02:44:53","bcr":null,"points":4.0,"status":null,"display_name":"Watercab","participant_type":"boat","sail_number":"CAN51421","raw_class":"Colgate 26","boat_name":"Watercab","boat_class":"Colgate 26","boat_id":307},{"rank":5,"fleet":null,"division":null,"phrf_rating":113,"start_time":"18:30:00","finish_time":"20:59:18","elapsed_time":"00 02:29:18","corrected_time":"00 02:48:43","bcr":null,"points":5.0,"status":null,"display_name":"Sly Fox","participant_type":"boat","sail_number":"34142","raw_class":"Chaser 29 Mod.","boat_name":"Sly Fox","boat_class":"Chaser 29 Mod.","boat_id":25},{"rank":6,"fleet":null,"division":null,"phrf_rating":null,"start_time":"18:30:00","finish_time":"21:02:13","elapsed_time":"00 02:32:13","corrected_time":"00 02:52:46","bcr":null,"points":6.0,"status":null,"display_name":"Beatnik","participant_type":"boat","sail_number":"186","raw_class":"K25","boat_name":"Beatnik","boat_class":"K25","boat_id":299},{"rank":7,"fleet":null,"division":null,"phrf_rating":126,"start_time":"18:30:00","finish_time":"20:50:24","elapsed_time":"00 02:20:24","corrected_time":"00 02:56:54","bcr":null,"points":7.0,"status":null,"display_name":"Poohsticks","participant_type":"boat","sail_number":"8","raw_class":"J/92","boat_name":"Poohsticks","boat_class":"J/92","boat_id":23},{"rank":11,"fleet":null,"division":null,"phrf_rating":null,"start_time":"18:30:00","finish_time":"00:00:00","elapsed_time":"00 00:00:00","corrected_time":"00 00:00:00","bcr":null,"points":11.0,"status":"DNF","display_name":"Awesome","participant_type":"boat","sail_number":"203","raw_class":"Kirby 25","boat_name":"Awesome","boat_class":"Kirby 25","boat_id":180},{"rank":11,"fleet":null,"division":null,"phrf_rating":null,"start_time":"18:30:00","finish_time":"00:00:00","elapsed_time":"00 00:00:00","corrected_time":"00 00:00:00","bcr":null,"points":11.0,"status":null,"display_name":"Sea Fever","participant_type":"boat","sail_number":"4514","raw_class":"CS30","boat_name":"Sea Fever","boat_class":"CS30","boat_id":105},{"rank":11,"fleet":null,"division":null,"phrf_rating":118,"start_time":"18:30:00","finish_time":"00:00:00","elapsed_time":"00 00:00:00","corrected_time":"00 00:00:00","bcr":null,"points":11.0,"status":"DNF","display_name":"Topaz","participant_type":"boat","sail_number":"M55","raw_class":"Mega 30","boat_name":"Topaz","boat_class":"Mega 30","boat_id":107}]},{"id":1256,"race_key":"r3","race_number":3,"date":"15/07/2004","start_time":"18:30:00","wind_direction":null,"wind_speed_knots":null,"course":null,"distance_nm":null,"notes":" 5 kts, Course: #24, Distance: 1","results":[{"rank":1,"fleet":null,"division":null,"phrf_rating":null,"start_time":"18:30:00","finish_time":"20:02:04","elapsed_time":"00 01:32:04","corrected_time":"00 01:44:30","bcr":null,"points":1.0,"status":null,"display_name":"Awesome","participant_type":"boat","sail_number":"203","raw_class":"Kirby 25","boat_name":"Awesome","boat_class":"Kirby 25","boat_id":180},{"rank":2,"fleet":null,"division":null,"phrf_rating":126,"start_time":"18:30:00","finish_time":"19:57:17","elapsed_time":"00 01:27:17","corrected_time":"00 01:49:59","bcr":null,"points":2.0,"status":null,"display_name":"Poohsticks","participant_type":"boat","sail_number":"8","raw_class":"J/92","boat_name":"Poohsticks","boat_class":"J/92","boat_id":23},{"rank":3,"fleet":null,"division":null,"phrf_rating":113,"start_time":"18:30:00","finish_time":"20:07:37","elapsed_time":"00 01:37:37","corrected_time":"00 01:50:18","bcr":null,"points":3.0,"status":null,"display_name":"Sly Fox","participant_type":"boat","sail_number":"34142","raw_class":"Chaser 29 Mod.","boat_name":"Sly Fox","boat_class":"Chaser 29 Mod.","boat_id":25},{"rank":4,"fleet":null,"division":null,"phrf_rating":null,"start_time":"18:30:00","finish_time":"20:20:25","elapsed_time":"00 01:50:25","corrected_time":"00 02:02:01","bcr":null,"points":4.0,"status":null,"display_name":"No Name","participant_type":"boat","sail_number":"31297","raw_class":"S2 7.9 IB","boat_name":"No Name","boat_class":"S2 7.9 IB","boat_id":305},{"rank":5,"fleet":null,"division":null,"phrf_rating":null,"start_time":"18:30:00","finish_time":"20:18:29","elapsed_time":"00 01:48:29","corrected_time":"00 02:03:08","bcr":null,"points":5.0,"status":null,"display_name":"Status Symbol","participant_type":"boat","sail_number":"126","raw_class":"Kirby 25","boat_name":"Status Symbol","boat_class":"Kirby 25","boat_id":265},{"rank":6,"fleet":null,"division":null,"phrf_rating":null,"start_time":"18:30:00","finish_time":"20:18:42","elapsed_time":"00 01:48:42","corrected_time":"00 02:04:28","bcr":null,"points":6.0,"status":null,"display_name":"Sea Fever","participant_type":"boat","sail_number":"4514","raw_class":"CS30","boat_name":"Sea Fever","boat_class":"CS30","boat_id":105},{"rank":7,"fleet":null,"division":null,"phrf_rating":null,"start_time":"18:30:00","finish_time":"20:20:37","elapsed_time":"00 01:50:37","corrected_time":"00 02:05:33","bcr":null,"points":7.0,"status":null,"display_name":"Beatnik","participant_type":"boat","sail_number":"186","raw_class":"K25","boat_name":"Beatnik","boat_class":"K25","boat_id":299},{"rank":8,"fleet":null,"division":null,"phrf_rating":118,"start_time":"18:30:00","finish_time":"20:17:22","elapsed_time":"00 01:47:22","corrected_time":"00 02:06:42","bcr":null,"points":8.0,"status":null,"display_name":"Topaz","participant_type":"boat","sail_number":"M55","raw_class":"Mega 30","boat_name":"Topaz","boat_class":"Mega 30","boat_id":107},{"rank":12,"fleet":null,"division":null,"phrf_rating":102,"start_time":"18:30:00","finish_time":"00:00:00","elapsed_time":"00 00:00:00","corrected_time":"00 00:00:00","bcr":null,"points":12.0,"status":"DNC","display_name":"Tsunami","participant_type":"boat","sail_number":"428","raw_class":"C&C 24","boat_name":"Tsunami","boat_class":"C&C 24","boat_id":43},{"rank":12,"fleet":null,"division":null,"phrf_rating":110,"start_time":"18:30:00","finish_time":"00:00:00","elapsed_time":"00 00:00:00","corrected_time":"00 00:00:00","bcr":null,"points":12.0,"status":"DNC","display_name":"Watercab","participant_type":"boat","sail_number":"CAN51421","raw_class":"Colgate 26","boat_name":"Watercab","boat_class":"Colgate 26","boat_id":307}]},{"id":1257,"race_key":"r4","race_number":4,"date":"22/07/2004","start_time":"18:30:00","wind_direction":null,"wind_speed_knots":null,"course":null,"distance_nm":null,"notes":", Course: #1, Distance: 1","results":[{"rank":1,"fleet":null,"division":null,"phrf_rating":null,"start_time":"18:30:00","finish_time":"20:05:19","elapsed_time":"00 01:35:19","corrected_time":"00 01:48:11","bcr":null,"points":1.0,"status":null,"display_name":"Awesome","participant_type":"boat","sail_number":"203","raw_class":"Kirby 25","boat_name":"Awesome","boat_class":"Kirby 25","boat_id":180},{"rank":2,"fleet":null,"division":null,"phrf_rating":118,"start_time":"18:30:00","finish_time":"20:04:39","elapsed_time":"00 01:34:39","corrected_time":"00 01:51:41","bcr":null,"points":2.0,"status":null,"display_name":"Topaz","participant_type":"boat","sail_number":"M55","raw_class":"Mega 30","boat_name":"Topaz","boat_class":"Mega 30","boat_id":107},{"rank":3,"fleet":null,"division":null,"phrf_rating":126,"start_time":"18:30:00","finish_time":"20:00:16","elapsed_time":"00 01:30:16","corrected_time":"00 01:53:44","bcr":null,"points":3.0,"status":null,"display_name":"Poohsticks","participant_type":"boat","sail_number":"8","raw_class":"J/92","boat_name":"Poohsticks","boat_class":"J/92","boat_id":23},{"rank":4,"fleet":null,"division":null,"phrf_rating":113,"start_time":"18:30:00","finish_time":"20:11:35","elapsed_time":"00 01:41:35","corrected_time":"00 01:54:47","bcr":null,"points":4.0,"status":null,"display_name":"Sly Fox","participant_type":"boat","sail_number":"34142","raw_class":"Chaser 29 Mod.","boat_name":"Sly Fox","boat_class":"Chaser 29 Mod.","boat_id":25},{"rank":5,"fleet":null,"division":null,"phrf_rating":null,"start_time":"18:30:00","finish_time":"20:14:20","elapsed_time":"00 01:44:20","corrected_time":"00 01:55:17","bcr":null,"points":5.0,"status":null,"display_name":"No Name","participant_type":"boat","sail_number":"31297","raw_class":"S2 7.9 IB","boat_name":"No Name","boat_class":"S2 7.9 IB","boat_id":305},{"rank":6,"fleet":null,"division":null,"phrf_rating":123,"start_time":"18:30:00","finish_time":"20:07:47","elapsed_time":"00 01:37:47","corrected_time":"00 02:00:16","bcr":null,"points":6.0,"status":null,"display_name":"Rumble Fish","participant_type":"boat","sail_number":"31991","raw_class":"J/29 I/B","boat_name":"Rumble Fish","boat_class":"J/29 I/B","boat_id":24},{"rank":7,"fleet":null,"division":null,"phrf_rating":null,"start_time":"18:30:00","finish_time":"20:18:50","elapsed_time":"00 01:48:50","corrected_time":"00 02:03:32","bcr":null,"points":7.0,"status":null,"display_name":"Beatnik","participant_type":"boat","sail_number":"186","raw_class":"K25","boat_name":"Beatnik","boat_class":"K25","boat_id":299},{"rank":8,"fleet":null,"division":null,"phrf_rating":null,"start_time":"18:30:00","finish_time":"20:19:48","elapsed_time":"00 01:49:48","corrected_time":"00 02:05:43","bcr":null,"points":8.0,"status":null,"display_name":"Sea Fever","participant_type":"boat","sail_number":"4514","raw_class":"CS30","boat_name":"Sea Fever","boat_class":"CS30","boat_id":105},{"rank":13,"fleet":null,"division":null,"phrf_rating":null,"start_time":"18:30:00","finish_time":"00:00:00","elapsed_time":"00 00:00:00","corrected_time":"00 00:00:00","bcr":null,"points":13.0,"status":"DNC","display_name":"Status Symbol","participant_type":"boat","sail_number":"126","raw_class":"Kirby 25","boat_name":"Status Symbol","boat_class":"Kirby 25","boat_id":265},{"rank":13,"fleet":null,"division":null,"phrf_rating":102,"start_time":"18:30:00","finish_time":"00:00:00","elapsed_time":"00 00:00:00","corrected_time":"00 00:00:00","bcr":null,"points":13.0,"status":"DNC","display_name":"Tsunami","participant_type":"boat","sail_number":"428","raw_class":"C&C 24","boat_name":"Tsunami","boat_class":"C&C 24","boat_id":43},{"rank":13,"fleet":null,"division":null,"phrf_rating":110,"start_time":"18:30:00","finish_time":"00:00:00","elapsed_time":"00 00:00:00","corrected_time":"00 00:00:00","bcr":null,"points":13.0,"status":"DNC","display_name":"Watercab","participant_type":"boat","sail_number":"CAN51421","raw_class":"Colgate 26","boat_name":"Watercab","boat_class":"Colgate 26","boat_id":307}]}]}