{"id":85,"year":2016,"name":"LYC Handicap - July TNS","canonical_name":"LYC Handicap - July TNS","slug":"lyc-handicap-july-tns","event_type":"tns","month":"july","source_format":"sailwave","source_file":"racing2014_2025/racing2016/july_TNS.htm","scoring_system":"Appendix A-LYC","rating_system":"PHRFTOT","races_sailed":4,"discards":1,"to_count":3,"entries":18,"publication_status":"as-of","published_at":null,"notes":null,"season_year":2016,"canonical_event_id":85,"is_variant_view":false,"variant_sources":[{"event_id":85,"name":"LYC Handicap - July TNS","source_file":"racing2014_2025/racing2016/july_TNS.htm","race_count":4,"standings_count":18,"result_count":46,"is_primary":true},{"event_id":86,"name":"LYC Handicap - July TNS Overall A, (B&S)","source_file":"racing2014_2025/racing2016/july_TNS_ab.htm","race_count":0,"standings_count":12,"result_count":0,"is_primary":false},{"event_id":87,"name":"LYC Handicap - July TNS Overall","source_file":"racing2014_2025/racing2016/july_TNS_overall.htm","race_count":0,"standings_count":12,"result_count":0,"is_primary":false}],"exclude_from_handicap_stats":false,"special_event_kind":null,"special_event_reasons":[],"standings":[{"rank":1,"summary_scope":"a_fleet","fleet":"A","division":null,"phrf_rating":99,"total_points":6.0,"nett_points":3.0,"display_name":"Poohsticks","participant_type":"boat","sail_number":"8","raw_class":"J/92","boat_name":"Poohsticks","boat_class":"J/92","boat_id":23},{"rank":2,"summary_scope":"a_fleet","fleet":"A","division":null,"phrf_rating":120,"total_points":14.0,"nett_points":6.0,"display_name":"Rumble Fish","participant_type":"boat","sail_number":"31991","raw_class":"J/29 I/B","boat_name":"Rumble Fish","boat_class":"J/29 I/B","boat_id":24},{"rank":3,"summary_scope":"a_fleet","fleet":"A","division":null,"phrf_rating":108,"total_points":11.0,"nett_points":7.0,"display_name":"Scotch Mist","participant_type":"boat","sail_number":"34429","raw_class":"J/29 O/B","boat_name":"Scotch Mist","boat_class":"J/29 O/B","boat_id":27},{"rank":4,"summary_scope":"a_fleet","fleet":"A","division":null,"phrf_rating":84,"total_points":15.0,"nett_points":10.0,"display_name":"Deep Bight","participant_type":"boat","sail_number":"89","raw_class":"J/88","boat_name":"Deep Bight","boat_class":"J/88","boat_id":69},{"rank":5,"summary_scope":"a_fleet","fleet":"A","division":null,"phrf_rating":87,"total_points":22.0,"nett_points":14.0,"display_name":"Mojo","participant_type":"boat","sail_number":"606","raw_class":"J/105","boat_name":"Mojo","boat_class":"J/105","boat_id":67},{"rank":6,"summary_scope":"a_fleet","fleet":"A","division":null,"phrf_rating":132,"total_points":24.0,"nett_points":16.0,"display_name":"Buzz","participant_type":"boat","sail_number":"7049","raw_class":"J/27","boat_name":"Buzz","boat_class":"J/27","boat_id":66},{"rank":1,"summary_scope":"overall","fleet":"S","division":null,"phrf_rating":171,"total_points":9.0,"nett_points":4.0,"display_name":"Shenanagans","participant_type":"boat","sail_number":"425","raw_class":"Sonar","boat_name":"Shenanagans","boat_class":"Sonar","boat_id":33},{"rank":2,"summary_scope":"overall","fleet":"S","division":null,"phrf_rating":171,"total_points":16.5,"nett_points":9.5,"display_name":"Echo","participant_type":"boat","sail_number":"571","raw_class":"Sonar","boat_name":"Echo","boat_class":"Sonar","boat_id":34},{"rank":3,"summary_scope":"overall","fleet":"A","division":null,"phrf_rating":99,"total_points":19.0,"nett_points":12.0,"display_name":"Poohsticks","participant_type":"boat","sail_number":"8","raw_class":"J/92","boat_name":"Poohsticks","boat_class":"J/92","boat_id":23},{"rank":4,"summary_scope":"overall","fleet":"S","division":null,"phrf_rating":171,"total_points":23.0,"nett_points":15.0,"display_name":"Model T","participant_type":"boat","sail_number":"462","raw_class":"Sonar","boat_name":"Model T","boat_class":"Sonar","boat_id":47},{"rank":5,"summary_scope":"overall","fleet":"A","division":null,"phrf_rating":120,"total_points":37.5,"nett_points":17.5,"display_name":"Rumble Fish","participant_type":"boat","sail_number":"31991","raw_class":"J/29 I/B","boat_name":"Rumble Fish","boat_class":"J/29 I/B","boat_id":24},{"rank":5,"summary_scope":"overall","fleet":"S","division":null,"phrf_rating":171,"total_points":30.0,"nett_points":16.0,"display_name":"Ping","participant_type":"boat","sail_number":"754","raw_class":"Sonar","boat_name":"Ping","boat_class":"Sonar","boat_id":45},{"rank":6,"summary_scope":"overall","fleet":"S","division":null,"phrf_rating":171,"total_points":38.0,"nett_points":18.0,"display_name":"SOT After","participant_type":"boat","sail_number":"835","raw_class":"Sonar","boat_name":"SOT After","boat_class":"Sonar","boat_id":59},{"rank":7,"summary_scope":"overall","fleet":"A","division":null,"phrf_rating":108,"total_points":29.0,"nett_points":20.0,"display_name":"Scotch Mist","participant_type":"boat","sail_number":"34429","raw_class":"J/29 O/B","boat_name":"Scotch Mist","boat_class":"J/29 O/B","boat_id":27},{"rank":9,"summary_scope":"overall","fleet":"A","division":null,"phrf_rating":84,"total_points":34.0,"nett_points":23.0,"display_name":"Deep Bight","participant_type":"boat","sail_number":"89","raw_class":"J/88","boat_name":"Deep Bight","boat_class":"J/88","boat_id":69},{"rank":9,"summary_scope":"overall","fleet":"S","division":null,"phrf_rating":171,"total_points":33.0,"nett_points":19.0,"display_name":"Pi","participant_type":"boat","sail_number":"415","raw_class":"Sonar","boat_name":"Pi","boat_class":"Sonar","boat_id":50},{"rank":11,"summary_scope":"overall","fleet":"A","division":null,"phrf_rating":87,"total_points":49.0,"nett_points":29.0,"display_name":"Mojo","participant_type":"boat","sail_number":"606","raw_class":"J/105","boat_name":"Mojo","boat_class":"J/105","boat_id":67},{"rank":12,"summary_scope":"overall","fleet":"A","division":null,"phrf_rating":132,"total_points":59.0,"nett_points":39.0,"display_name":"Buzz","participant_type":"boat","sail_number":"7049","raw_class":"J/27","boat_name":"Buzz","boat_class":"J/27","boat_id":66},{"rank":13,"summary_scope":"overall","fleet":"S","division":null,"phrf_rating":171,"total_points":63.0,"nett_points":43.0,"display_name":"Scamp","participant_type":"boat","sail_number":"17","raw_class":"Sonar","boat_name":"Scamp","boat_class":"Sonar","boat_id":35},{"rank":14,"summary_scope":"overall","fleet":"A","division":null,"phrf_rating":45,"total_points":67.0,"nett_points":47.0,"display_name":"Odyssey","participant_type":"boat","sail_number":"151165","raw_class":"Swan 57","boat_name":"Odyssey","boat_class":"Swan 57","boat_id":55},{"rank":15,"summary_scope":"overall","fleet":"S","division":null,"phrf_rating":171,"total_points":70.0,"nett_points":50.0,"display_name":"Martha Jane","participant_type":"boat","sail_number":"624","raw_class":"Sonar","boat_name":"Martha Jane","boat_class":"Sonar","boat_id":48},{"rank":16,"summary_scope":"overall","fleet":"B","division":null,"phrf_rating":213,"total_points":72.0,"nett_points":52.0,"display_name":"Big Fish","participant_type":"boat","sail_number":"40930","raw_class":"Newport 28","boat_name":"Big Fish","boat_class":"Newport 28","boat_id":26},{"rank":17,"summary_scope":"overall","fleet":"A","division":null,"phrf_rating":54,"total_points":72.0,"nett_points":52.0,"display_name":"Wandrian","participant_type":"boat","sail_number":"50141","raw_class":"Taylor 41","boat_name":"Wandrian","boat_class":"Taylor 41","boat_id":28},{"rank":18,"summary_scope":"overall","fleet":"A","division":null,"phrf_rating":114,"total_points":79.0,"nett_points":59.0,"display_name":"Paradigm Shift","participant_type":"boat","sail_number":"117","raw_class":"J/29 O/B","boat_name":"Paradigm Shift","boat_class":"J/29 O/B","boat_id":32},{"rank":1,"summary_scope":"s_fleet","fleet":"S","division":null,"phrf_rating":171,"total_points":8.0,"nett_points":4.0,"display_name":"Shenanagans","participant_type":"boat","sail_number":"425","raw_class":"Sonar","boat_name":"Shenanagans","boat_class":"Sonar","boat_id":33},{"rank":2,"summary_scope":"s_fleet","fleet":"S","division":null,"phrf_rating":171,"total_points":13.0,"nett_points":8.0,"display_name":"Echo","participant_type":"boat","sail_number":"571","raw_class":"Sonar","boat_name":"Echo","boat_class":"Sonar","boat_id":34},{"rank":3,"summary_scope":"s_fleet","fleet":"S","division":null,"phrf_rating":171,"total_points":18.0,"nett_points":10.0,"display_name":"Ping","participant_type":"boat","sail_number":"754","raw_class":"Sonar","boat_name":"Ping","boat_class":"Sonar","boat_id":45},{"rank":4,"summary_scope":"s_fleet","fleet":"S","division":null,"phrf_rating":171,"total_points":16.0,"nett_points":11.0,"display_name":"Model T","participant_type":"boat","sail_number":"462","raw_class":"Sonar","boat_name":"Model T","boat_class":"Sonar","boat_id":47},{"rank":5,"summary_scope":"s_fleet","fleet":"S","division":null,"phrf_rating":171,"total_points":20.0,"nett_points":12.0,"display_name":"SOT After","participant_type":"boat","sail_number":"835","raw_class":"Sonar","boat_name":"SOT After","boat_class":"Sonar","boat_id":59},{"rank":6,"summary_scope":"s_fleet","fleet":"S","division":null,"phrf_rating":171,"total_points":21.0,"nett_points":13.0,"display_name":"Pi","participant_type":"boat","sail_number":"415","raw_class":"Sonar","boat_name":"Pi","boat_class":"Sonar","boat_id":50}],"races":[{"id":204,"race_key":"r1","race_number":1,"date":"07/07/16","start_time":"18:41:02","wind_direction":null,"wind_speed_knots":null,"course":null,"distance_nm":null,"notes":"Start: A, Finishes: Finish time, Time: 18:41:02","results":[{"rank":1,"fleet":"S","division":null,"phrf_rating":171,"start_time":"18:35:00","finish_time":"20:01:09","elapsed_time":"1:26:09","corrected_time":"1:26:02","bcr":null,"points":1.0,"status":null,"display_name":"Ping","participant_type":"boat","sail_number":"754","raw_class":"Sonar","boat_name":"Ping","boat_class":"Sonar","boat_id":45},{"rank":2,"fleet":"S","division":null,"phrf_rating":171,"start_time":"18:35:00","finish_time":"20:02:59","elapsed_time":"1:27:59","corrected_time":"1:27:51","bcr":null,"points":2.0,"status":null,"display_name":"Echo","participant_type":"boat","sail_number":"571","raw_class":"Sonar","boat_name":"Echo","boat_class":"Sonar","boat_id":34},{"rank":3,"fleet":"A","division":null,"phrf_rating":108,"start_time":"18:41:02","finish_time":"20:01:55","elapsed_time":"1:20:53","corrected_time":"1:28:48","bcr":null,"points":3.0,"status":null,"display_name":"Scotch Mist","participant_type":"boat","sail_number":"34429","raw_class":"J/29 O/B","boat_name":"Scotch Mist","boat_class":"J/29 O/B","boat_id":27},{"rank":4,"fleet":"S","division":null,"phrf_rating":171,"start_time":"18:35:00","finish_time":"20:03:57","elapsed_time":"1:28:57","corrected_time":"1:28:49","bcr":null,"points":4.0,"status":null,"display_name":"Model T","participant_type":"boat","sail_number":"462","raw_class":"Sonar","boat_name":"Model T","boat_class":"Sonar","boat_id":47},{"rank":5,"fleet":"S","division":null,"phrf_rating":171,"start_time":"18:35:00","finish_time":"20:04:46","elapsed_time":"1:29:46","corrected_time":"1:29:38","bcr":null,"points":5.0,"status":null,"display_name":"Shenanagans","participant_type":"boat","sail_number":"425","raw_class":"Sonar","boat_name":"Shenanagans","boat_class":"Sonar","boat_id":33},{"rank":6,"fleet":"A","division":null,"phrf_rating":120,"start_time":"18:41:02","finish_time":"20:06:37","elapsed_time":"1:25:35","corrected_time":"1:32:13","bcr":null,"points":6.0,"status":null,"display_name":"Rumble Fish","participant_type":"boat","sail_number":"31991","raw_class":"J/29 I/B","boat_name":"Rumble Fish","boat_class":"J/29 I/B","boat_id":24},{"rank":7,"fleet":"A","division":null,"phrf_rating":99,"start_time":"18:41:02","finish_time":"20:05:13","elapsed_time":"1:24:11","corrected_time":"1:33:46","bcr":null,"points":7.0,"status":null,"display_name":"Poohsticks","participant_type":"boat","sail_number":"8","raw_class":"J/92","boat_name":"Poohsticks","boat_class":"J/92","boat_id":23},{"rank":8,"fleet":"A","division":null,"phrf_rating":84,"start_time":"18:41:02","finish_time":"20:03:20","elapsed_time":"1:22:18","corrected_time":"1:33:55","bcr":null,"points":8.0,"status":null,"display_name":"Deep Bight","participant_type":"boat","sail_number":"89","raw_class":"J/88","boat_name":"Deep Bight","boat_class":"J/88","boat_id":69},{"rank":9,"fleet":"A","division":null,"phrf_rating":87,"start_time":"18:41:02","finish_time":"20:04:48","elapsed_time":"1:23:46","corrected_time":"1:35:08","bcr":null,"points":9.0,"status":null,"display_name":"Mojo","participant_type":"boat","sail_number":"606","raw_class":"J/105","boat_name":"Mojo","boat_class":"J/105","boat_id":67},{"rank":10,"fleet":"S","division":null,"phrf_rating":171,"start_time":"18:35:00","finish_time":"20:11:42","elapsed_time":"1:36:42","corrected_time":"1:36:34","bcr":null,"points":10.0,"status":null,"display_name":"Martha Jane","participant_type":"boat","sail_number":"624","raw_class":"Sonar","boat_name":"Martha Jane","boat_class":"Sonar","boat_id":48},{"rank":11,"fleet":"A","division":null,"phrf_rating":114,"start_time":"","finish_time":"","elapsed_time":"RAF","corrected_time":"","bcr":null,"points":19.0,"status":null,"display_name":"Paradigm Shift","participant_type":"boat","sail_number":"117","raw_class":"J/29 O/B","boat_name":"Paradigm Shift","boat_class":"J/29 O/B","boat_id":32}]},{"id":205,"race_key":"r2","race_number":2,"date":"14/07/16","start_time":"18:36:30","wind_direction":null,"wind_speed_knots":null,"course":null,"distance_nm":null,"notes":"Start: A, Finishes: Finish time, Time: 18:36:30","results":[{"rank":1,"fleet":"S","division":null,"phrf_rating":171,"start_time":"18:42:30","finish_time":"19:57:05","elapsed_time":"1:14:35","corrected_time":"1:14:29","bcr":null,"points":1.0,"status":null,"display_name":"Shenanagans","participant_type":"boat","sail_number":"425","raw_class":"Sonar","boat_name":"Shenanagans","boat_class":"Sonar","boat_id":33},{"rank":2,"fleet":"S","division":null,"phrf_rating":171,"start_time":"18:42:30","finish_time":"19:57:34","elapsed_time":"1:15:04","corrected_time":"1:14:58","bcr":null,"points":2.0,"status":null,"display_name":"Echo","participant_type":"boat","sail_number":"571","raw_class":"Sonar","boat_name":"Echo","boat_class":"Sonar","boat_id":34},{"rank":3,"fleet":"A","division":null,"phrf_rating":99,"start_time":"18:36:30","finish_time":"19:44:45","elapsed_time":"1:08:15","corrected_time":"1:16:01","bcr":null,"points":3.0,"status":null,"display_name":"Poohsticks","participant_type":"boat","sail_number":"8","raw_class":"J/92","boat_name":"Poohsticks","boat_class":"J/92","boat_id":23},{"rank":4,"fleet":"S","division":null,"phrf_rating":171,"start_time":"18:42:30","finish_time":"19:58:45","elapsed_time":"1:16:15","corrected_time":"1:16:08","bcr":null,"points":4.0,"status":null,"display_name":"SOT After","participant_type":"boat","sail_number":"835","raw_class":"Sonar","boat_name":"SOT After","boat_class":"Sonar","boat_id":59},{"rank":5,"fleet":"S","division":null,"phrf_rating":171,"start_time":"18:42:30","finish_time":"19:59:16","elapsed_time":"1:16:46","corrected_time":"1:16:39","bcr":null,"points":5.0,"status":null,"display_name":"Model T","participant_type":"boat","sail_number":"462","raw_class":"Sonar","boat_name":"Model T","boat_class":"Sonar","boat_id":47},{"rank":6,"fleet":"A","division":null,"phrf_rating":132,"start_time":"18:36:30","finish_time":"19:49:06","elapsed_time":"1:12:36","corrected_time":"1:16:48","bcr":null,"points":6.0,"status":null,"display_name":"Rumble Fish","participant_type":"boat","sail_number":"31991","raw_class":"J/29 I/B","boat_name":"Rumble Fish","boat_class":"J/29 I/B","boat_id":24},{"rank":7,"fleet":"A","division":null,"phrf_rating":63,"start_time":"18:36:30","finish_time":"19:41:35","elapsed_time":"1:05:05","corrected_time":"1:16:56","bcr":null,"points":7.0,"status":null,"display_name":"Odyssey","participant_type":"boat","sail_number":"151165","raw_class":"Swan 57","boat_name":"Odyssey","boat_class":"Swan 57","boat_id":55},{"rank":8,"fleet":"A","division":null,"phrf_rating":84,"start_time":"18:36:30","finish_time":"19:45:56","elapsed_time":"1:09:26","corrected_time":"1:19:14","bcr":null,"points":8.0,"status":null,"display_name":"Deep Bight","participant_type":"boat","sail_number":"89","raw_class":"J/88","boat_name":"Deep Bight","boat_class":"J/88","boat_id":69},{"rank":9,"fleet":"A","division":null,"phrf_rating":108,"start_time":"18:36:30","finish_time":"19:48:47","elapsed_time":"1:12:17","corrected_time":"1:19:22","bcr":null,"points":9.0,"status":null,"display_name":"Scotch Mist","participant_type":"boat","sail_number":"34429","raw_class":"J/29 O/B","boat_name":"Scotch Mist","boat_class":"J/29 O/B","boat_id":27},{"rank":10,"fleet":"A","division":null,"phrf_rating":87,"start_time":"18:36:30","finish_time":"19:47:22","elapsed_time":"1:10:52","corrected_time":"1:20:29","bcr":null,"points":10.0,"status":null,"display_name":"Mojo","participant_type":"boat","sail_number":"606","raw_class":"J/105","boat_name":"Mojo","boat_class":"J/105","boat_id":67},{"rank":11,"fleet":"A","division":null,"phrf_rating":132,"start_time":"18:36:30","finish_time":"19:52:37","elapsed_time":"1:16:07","corrected_time":"1:20:31","bcr":null,"points":11.0,"status":null,"display_name":"Buzz","participant_type":"boat","sail_number":"7049","raw_class":"J/27","boat_name":"Buzz","boat_class":"J/27","boat_id":66},{"rank":12,"fleet":"A","division":null,"phrf_rating":72,"start_time":"18:36:30","finish_time":"19:45:58","elapsed_time":"1:09:28","corrected_time":"1:20:52","bcr":null,"points":12.0,"status":null,"display_name":"Wandrian","participant_type":"boat","sail_number":"50141","raw_class":"Taylor 41","boat_name":"Wandrian","boat_class":"Taylor 41","boat_id":28}]},{"id":206,"race_key":"r3","race_number":3,"date":"21/07/16","start_time":"18:35:00","wind_direction":null,"wind_speed_knots":null,"course":null,"distance_nm":null,"notes":"Start: A, Finishes: Finish time, Time: 18:35:00","results":[{"rank":1,"fleet":"S","division":null,"phrf_rating":171,"start_time":"18:29:00","finish_time":"19:51:57","elapsed_time":"1:22:57","corrected_time":"1:22:50","bcr":null,"points":1.0,"status":null,"display_name":"Shenanagans","participant_type":"boat","sail_number":"425","raw_class":"Sonar","boat_name":"Shenanagans","boat_class":"Sonar","boat_id":33},{"rank":2,"fleet":"S","division":null,"phrf_rating":171,"start_time":"18:29:00","finish_time":"19:53:16","elapsed_time":"1:24:16","corrected_time":"1:24:09","bcr":null,"points":2.0,"status":null,"display_name":"Pi","participant_type":"boat","sail_number":"415","raw_class":"Sonar","boat_name":"Pi","boat_class":"Sonar","boat_id":50},{"rank":3,"fleet":"S","division":null,"phrf_rating":171,"start_time":"18:29:00","finish_time":"19:53:23","elapsed_time":"1:24:23","corrected_time":"1:24:16","bcr":null,"points":3.0,"status":null,"display_name":"Scamp","participant_type":"boat","sail_number":"17","raw_class":"Sonar","boat_name":"Scamp","boat_class":"Sonar","boat_id":35},{"rank":4,"fleet":"S","division":null,"phrf_rating":171,"start_time":"18:29:00","finish_time":"19:53:58","elapsed_time":"1:24:58","corrected_time":"1:24:51","bcr":null,"points":4.0,"status":null,"display_name":"SOT After","participant_type":"boat","sail_number":"835","raw_class":"Sonar","boat_name":"SOT After","boat_class":"Sonar","boat_id":59},{"rank":5,"fleet":"A","division":null,"phrf_rating":99,"start_time":"18:35:00","finish_time":"19:51:35","elapsed_time":"1:16:35","corrected_time":"1:25:18","bcr":null,"points":5.0,"status":null,"display_name":"Poohsticks","participant_type":"boat","sail_number":"8","raw_class":"J/92","boat_name":"Poohsticks","boat_class":"J/92","boat_id":23},{"rank":6,"fleet":"S","division":null,"phrf_rating":171,"start_time":"18:29:00","finish_time":"19:54:39","elapsed_time":"1:25:39","corrected_time":"1:25:32","bcr":null,"points":6.0,"status":null,"display_name":"Model T","participant_type":"boat","sail_number":"462","raw_class":"Sonar","boat_name":"Model T","boat_class":"Sonar","boat_id":47},{"rank":7,"fleet":"S","division":null,"phrf_rating":171,"start_time":"18:29:00","finish_time":"19:54:49","elapsed_time":"1:25:49","corrected_time":"1:25:42","bcr":null,"points":7.0,"status":null,"display_name":"Echo","participant_type":"boat","sail_number":"571","raw_class":"Sonar","boat_name":"Echo","boat_class":"Sonar","boat_id":34},{"rank":8,"fleet":"A","division":null,"phrf_rating":108,"start_time":"18:35:00","finish_time":"19:53:28","elapsed_time":"1:18:28","corrected_time":"1:26:09","bcr":null,"points":8.0,"status":null,"display_name":"Scotch Mist","participant_type":"boat","sail_number":"34429","raw_class":"J/29 O/B","boat_name":"Scotch Mist","boat_class":"J/29 O/B","boat_id":27},{"rank":9,"fleet":"A","division":null,"phrf_rating":132,"start_time":"18:35:00","finish_time":"19:56:44","elapsed_time":"1:21:44","corrected_time":"1:26:28","bcr":null,"points":9.0,"status":null,"display_name":"Buzz","participant_type":"boat","sail_number":"7049","raw_class":"J/27","boat_name":"Buzz","boat_class":"J/27","boat_id":66},{"rank":10,"fleet":"A","division":null,"phrf_rating":87,"start_time":"18:35:00","finish_time":"19:51:13","elapsed_time":"1:16:13","corrected_time":"1:26:33","bcr":null,"points":10.0,"status":null,"display_name":"Mojo","participant_type":"boat","sail_number":"606","raw_class":"J/105","boat_name":"Mojo","boat_class":"J/105","boat_id":67},{"rank":11,"fleet":"A","division":null,"phrf_rating":84,"start_time":"18:35:00","finish_time":"19:52:06","elapsed_time":"1:17:06","corrected_time":"1:27:59","bcr":null,"points":11.0,"status":null,"display_name":"Deep Bight","participant_type":"boat","sail_number":"89","raw_class":"J/88","boat_name":"Deep Bight","boat_class":"J/88","boat_id":69},{"rank":12,"fleet":"B","division":null,"phrf_rating":213,"start_time":"18:29:00","finish_time":"20:09:56","elapsed_time":"1:40:56","corrected_time":"1:35:03","bcr":null,"points":12.0,"status":null,"display_name":"Big Fish","participant_type":"boat","sail_number":"40930","raw_class":"Newport 28","boat_name":"Big Fish","boat_class":"Newport 28","boat_id":26}]},{"id":207,"race_key":"r4","race_number":4,"date":"28/07/16","start_time":"18:36:00","wind_direction":null,"wind_speed_knots":null,"course":null,"distance_nm":null,"notes":"Start: A, Finishes: Finish time, Time: 18:36:00","results":[{"rank":1,"fleet":"S","division":null,"phrf_rating":171,"start_time":"18:30:00","finish_time":"19:37:39","elapsed_time":"1:07:39","corrected_time":"1:07:33","bcr":null,"points":1.0,"status":null,"display_name":"Ping","participant_type":"boat","sail_number":"754","raw_class":"Sonar","boat_name":"Ping","boat_class":"Sonar","boat_id":45},{"rank":2,"fleet":"S","division":null,"phrf_rating":171,"start_time":"18:30:00","finish_time":"19:38:46","elapsed_time":"1:08:46","corrected_time":"1:08:40","bcr":null,"points":2.0,"status":null,"display_name":"Shenanagans","participant_type":"boat","sail_number":"425","raw_class":"Sonar","boat_name":"Shenanagans","boat_class":"Sonar","boat_id":33},{"rank":3,"fleet":"S","division":null,"phrf_rating":171,"start_time":"18:30:00","finish_time":"19:39:06","elapsed_time":"1:09:06","corrected_time":"1:09:00","bcr":null,"points":3.0,"status":null,"display_name":"Pi","participant_type":"boat","sail_number":"415","raw_class":"Sonar","boat_name":"Pi","boat_class":"Sonar","boat_id":50},{"rank":4,"fleet":"A","division":null,"phrf_rating":99,"start_time":"18:36:00","finish_time":"19:38:00","elapsed_time":"1:02:00","corrected_time":"1:09:03","bcr":null,"points":4.0,"status":null,"display_name":"Poohsticks","participant_type":"boat","sail_number":"8","raw_class":"J/92","boat_name":"Poohsticks","boat_class":"J/92","boat_id":23},{"rank":5,"fleet":"S","division":null,"phrf_rating":171,"start_time":"18:30:00","finish_time":"19:39:14","elapsed_time":"1:09:14","corrected_time":"1:09:08","bcr":null,"points":5.5,"status":null,"display_name":"Echo","participant_type":"boat","sail_number":"571","raw_class":"Sonar","boat_name":"Echo","boat_class":"Sonar","boat_id":34},{"rank":5,"fleet":"A","division":null,"phrf_rating":120,"start_time":"18:36:00","finish_time":"19:40:10","elapsed_time":"1:04:10","corrected_time":"1:09:08","bcr":null,"points":5.5,"status":null,"display_name":"Rumble Fish","participant_type":"boat","sail_number":"31991","raw_class":"J/29 I/B","boat_name":"Rumble Fish","boat_class":"J/29 I/B","boat_id":24},{"rank":7,"fleet":"A","division":null,"phrf_rating":84,"start_time":"18:36:00","finish_time":"19:37:10","elapsed_time":"1:01:10","corrected_time":"1:09:48","bcr":null,"points":7.0,"status":null,"display_name":"Deep Bight","participant_type":"boat","sail_number":"89","raw_class":"J/88","boat_name":"Deep Bight","boat_class":"J/88","boat_id":69},{"rank":8,"fleet":"S","division":null,"phrf_rating":171,"start_time":"18:30:00","finish_time":"19:40:05","elapsed_time":"1:10:05","corrected_time":"1:09:59","bcr":null,"points":8.0,"status":null,"display_name":"Model T","participant_type":"boat","sail_number":"462","raw_class":"Sonar","boat_name":"Model T","boat_class":"Sonar","boat_id":47},{"rank":9,"fleet":"A","division":null,"phrf_rating":108,"start_time":"18:36:00","finish_time":"19:39:50","elapsed_time":"1:03:50","corrected_time":"1:10:05","bcr":null,"points":9.0,"status":null,"display_name":"Scotch Mist","participant_type":"boat","sail_number":"34429","raw_class":"J/29 O/B","boat_name":"Scotch Mist","boat_class":"J/29 O/B","boat_id":27},{"rank":10,"fleet":"S","division":null,"phrf_rating":171,"start_time":"18:30:00","finish_time":"19:40:35","elapsed_time":"1:10:35","corrected_time":"1:10:29","bcr":null,"points":10.0,"status":null,"display_name":"SOT After","participant_type":"boat","sail_number":"835","raw_class":"Sonar","boat_name":"SOT After","boat_class":"Sonar","boat_id":59},{"rank":11,"fleet":"A","division":null,"phrf_rating":132,"start_time":"18:36:00","finish_time":"","elapsed_time":"OCS","corrected_time":"","bcr":null,"points":19.0,"status":null,"display_name":"Buzz","participant_type":"boat","sail_number":"7049","raw_class":"J/27","boat_name":"Buzz","boat_class":"J/27","boat_id":66}]}]}